sp/__init__.py
sp/demos.py
sp/main.py
sp/test_mocks.py
sp/upgrade_check.py
sp/commands/__init__.py
sp/commands/init.py
sp/commands/lab.py
sp/commands/upgrade.py
sp/core/__init__.py
sp/core/config.py
sp/core/environment.py
sp/core/jupyter.py
sp/ui/__init__.py
sp/ui/console.py
signalpilot-0.7.1.dist-info/METADATA
signalpilot-0.7.1.dist-info/WHEEL
signalpilot-0.7.1.dist-info/entry_points.txt
signalpilot-0.7.1.dist-info/licenses/LICENSE
signalpilot-0.7.1.dist-info/RECORD
