Metadata-Version: 2.4
Name: signalpilot
Version: 0.7.1
Summary: SignalPilot Installer CLI - Your Trusted CoPilot for Data Analysis
Project-URL: Homepage, https://signalpilot.ai
Project-URL: Repository, https://github.com/SignalPilot-Labs/signalpilot-cli
Project-URL: Documentation, https://signalpilot.ai/docs
Author-email: "SignalPilot Inc." <info@signalpilot.ai>
License: MIT
License-File: LICENSE
Keywords: ai,copilot,data-analysis,jupyter,notebook
Classifier: Development Status :: 3 - Alpha
Classifier: Framework :: Jupyter
Classifier: Framework :: Jupyter :: JupyterLab
Classifier: Framework :: Jupyter :: JupyterLab :: 4
Classifier: Intended Audience :: Developers
Classifier: Intended Audience :: Science/Research
Classifier: License :: OSI Approved :: MIT License
Classifier: Programming Language :: Python :: 3
Classifier: Programming Language :: Python :: 3.10
Classifier: Programming Language :: Python :: 3.11
Classifier: Programming Language :: Python :: 3.12
Classifier: Topic :: Scientific/Engineering
Classifier: Topic :: Software Development
Requires-Python: >=3.10
Requires-Dist: rich>=13.0.0
Requires-Dist: typer>=0.12.0
Provides-Extra: dev
Requires-Dist: pytest>=8.0.0; extra == 'dev'
